Metadata-Version: 2.1
Name: odoo14-addon-l10n_br_zip
Version: 14.0.2.3.2
Summary: Brazilian Localisation ZIP Codes
Home-page: https://github.com/OCA/l10n-brazil
Author: Akretion, Odoo Community Association (OCA)
Author-email: support@odoo-community.org
License: AGPL-3
Classifier: Programming Language :: Python
Classifier: Framework :: Odoo
Classifier: Framework :: Odoo :: 14.0
Classifier: License :: OSI Approved :: GNU Affero General Public License v3
Classifier: Development Status :: 6 - Mature
Requires-Python: >=3.6
Requires-Dist: brazilcep
Requires-Dist: erpbrasil.base
Requires-Dist: odoo14-addon-l10n-br-base
Requires-Dist: odoo<14.1dev,>=14.0a
